massql/__init__.py
massql/msql.ebnf
massql/msql_cmd.py
massql/msql_engine.py
massql/msql_engine_filters.py
massql/msql_extract.py
massql/msql_fileloading.py
massql/msql_parser.py
massql/msql_translator.py
massql/msql_visualizer.py
massql-2025.6.18.data/scripts/msql_cmd.py
massql-2025.6.18.dist-info/licenses/LICENSE.txt
massql-2025.6.18.dist-info/METADATA
massql-2025.6.18.dist-info/WHEEL
massql-2025.6.18.dist-info/entry_points.txt
massql-2025.6.18.dist-info/top_level.txt
massql-2025.6.18.dist-info/RECORD
