Metadata-Version: 2.4
Name: massql
Version: 2025.6.18
Summary: Mass spectrometry query language python implementation
Home-page: https://github.com/mwang87/MassQueryLanguage
Author: Mingxun Wang
Author-email: mwang87@gmail.com
Project-URL: Bug Tracker, https://github.com/mwang87/MassQueryLanguage/issues
Project-URL: Documentation, https://mwang87.github.io/MassQueryLanguage_Documentation/
Classifier: Programming Language :: Python :: 3
Classifier: License :: OSI Approved :: MIT License
Classifier: Operating System :: OS Independent
Requires-Python: >=3.6
License-File: LICENSE.txt
Requires-Dist: pymzml
Requires-Dist: lark-parser
Requires-Dist: pandas
Requires-Dist: pyarrow
Requires-Dist: tqdm
Requires-Dist: py_expression_eval
Requires-Dist: matchms
Requires-Dist: pyteomics
Requires-Dist: psims
Requires-Dist: plotly
Requires-Dist: kaleido
Requires-Dist: pydot
Requires-Dist: pyyaml
Dynamic: author
Dynamic: author-email
Dynamic: classifier
Dynamic: description
Dynamic: description-content-type
Dynamic: home-page
Dynamic: license-file
Dynamic: project-url
Dynamic: requires-dist
Dynamic: requires-python
Dynamic: summary
